solit
