Metadata-Version: 1.0
Name: solit
Version: 0.4
Summary: The Logstash Integration Test framework
Home-page: http://github.com/elastic/solit
Author: Nick Lang
Author-email: nick.lang@elastic.co
License: Apache v2
Platform: UNKNOWN
